<?xml version="1.0" encoding="utf-8"?>
<ImportExportXml xmlns:xsi="http://www.w3.org/2001/XMLSchema-instance">
  <Entities />
  <Roles />
  <Workflows />
  <FieldSecurityProfiles />
  <Templates />
  <EntityMaps />
  <EntityRelationships />
  <OrganizationSettings />
  <optionsets />
  <CustomControls />
  <AppModuleSiteMaps />
  <AppModules />
  <EntityDataProviders />
  <CanvasApps />
  <connectionreferences>
    <connectionreference connectionreferencelogicalname="bac_sharedapprovals_4d2f6">
      <connectionreferencedisplayname>Approvals OrganizationalPackageReview-4d2f6</connectionreferencedisplayname>
      <connectorid>/providers/Microsoft.PowerApps/apis/shared_approvals</connectorid>
      <iscustomizable>1</iscustomizable>
      <statecode>0</statecode>
      <statuscode>1</statuscode>
    </connectionreference>
    <connectionreference connectionreferencelogicalname="bac_sharedcommondataserviceforapps_32f20">
      <connectionreferencedisplayname>Common Data Service (current environment)</connectionreferencedisplayname>
      <connectorid>/providers/Microsoft.PowerApps/apis/shared_commondataserviceforapps</connectorid>
      <iscustomizable>1</iscustomizable>
      <statecode>0</statecode>
      <statuscode>1</statuscode>
    </connectionreference>
    <connectionreference connectionreferencelogicalname="bac_sharedcommondataserviceforapps_64668">
      <connectionreferencedisplayname>Microsoft Dataverse DataStarterKit-64668</connectionreferencedisplayname>
      <connectorid>/providers/Microsoft.PowerApps/apis/shared_commondataserviceforapps</connectorid>
      <iscustomizable>1</iscustomizable>
      <statecode>0</statecode>
      <statuscode>1</statuscode>
    </connectionreference>
  </connectionreferences>
  <Languages>
    <Language>1033</Language>
  </Languages>
</ImportExportXml>